catty/__init__.py
catty/words.py
catty-0.1.1.dist-info/LICENSE
catty-0.1.1.dist-info/METADATA
catty-0.1.1.dist-info/WHEEL
catty-0.1.1.dist-info/top_level.txt
catty-0.1.1.dist-info/RECORD
