Metadata-Version: 2.1
Name: catty
Version: 0.1.1
Summary: Concatenative programming integrated to Python
Home-page: https://github.com/hamelin/catty
Author: Benoit Hamelin
Author-email: benoit@benoithamelin.com
License: UNKNOWN
Platform: UNKNOWN
Classifier: Development Status :: 3 - Alpha
Classifier: Intended Audience :: Developers
Classifier: License :: OSI Approved :: MIT License
Classifier: Programming Language :: Python :: 3
Classifier: Topic :: Software Development :: Interpreters
Requires-Python: >=3.7
License-File: LICENSE
